videofy/__init__.py
videofy/__main__.py
videofy/frames.py
videofy/py.typed
videofy-0.1.1.dist-info/entry_points.txt
videofy-0.1.1.dist-info/LICENSE.rst
videofy-0.1.1.dist-info/WHEEL
videofy-0.1.1.dist-info/METADATA
videofy-0.1.1.dist-info/RECORD
