Metadata-Version: 2.1
Name: videofy
Version: 0.1.1
Summary: Videofy
Home-page: https://github.com/Daem0n-th/videofy
License: MIT
Author: Daem0n-th
Author-email: daem0nth.mail@gmail.com
Requires-Python: >=3.6.1,<4.0.0
Classifier: Development Status :: 2 - Pre-Alpha
Classifier: License :: OSI Approved :: MIT License
Classifier: Programming Language :: Python :: 3
Classifier: Programming Language :: Python :: 3.6
Classifier: Programming Language :: Python :: 3.7
Classifier: Programming Language :: Python :: 3.8
Classifier: Programming Language :: Python :: 3.9
Requires-Dist: click (>=8.0.1,<9.0.0)
Requires-Dist: imageio-ffmpeg (>=0.4.4,<0.5.0)
Project-URL: Changelog, https://github.com/Daem0n-th/videofy/releases
Project-URL: Documentation, https://videofy.readthedocs.io
Project-URL: Repository, https://github.com/Daem0n-th/videofy
